pymushra/__init__.py
pymushra/casting.py
pymushra/cli.py
pymushra/service.py
pymushra/stats.py
pymushra/utils.py
pymushra/wsgi.py
pymushra/templates/base.html
pymushra/templates/admin/info.html
pymushra/templates/admin/list.html
pymushra/templates/admin/table.html
pymushra/templates/error/404.html
pymushra/templates/error/error.html
pymushra/templates/stats/mushra.html
pymushra-0.4.dist-info/METADATA
pymushra-0.4.dist-info/WHEEL
pymushra-0.4.dist-info/entry_points.txt
pymushra-0.4.dist-info/licenses/LICENSE
pymushra-0.4.dist-info/RECORD
