Metadata-Version: 2.4
Name: pymushra
Version: 0.4
Summary: webMUSHRA server in Python
Author-email: Nils Werner <nils.werner@audiolabs-erlangen.de>, Fabian-Robert Stöter <fabian-robert.stoeter@audiolabs-erlangen.de>
License-Expression: MIT
License-File: LICENSE
Requires-Python: >=3.7
Requires-Dist: click
Requires-Dist: flask>=2.2.5
Requires-Dist: ipython
Requires-Dist: matplotlib>=2.0.0
Requires-Dist: numpy
Requires-Dist: pandas
Requires-Dist: patsy
Requires-Dist: scipy
Requires-Dist: seaborn
Requires-Dist: statsmodels
Requires-Dist: tinydb>=3.0.0
Requires-Dist: tinyrecord
